statux/__init__.py
statux/_conversions.py
statux/_errors.py
statux/battery.py
statux/cpu.py
statux/cpu_OLD.py
statux/disk_dev.py
statux/disks.py
statux/net.py
statux/ram.py
statux/system.py
statux/temp.py
statux-0.1.2.dist-info/LICENSE
statux-0.1.2.dist-info/METADATA
statux-0.1.2.dist-info/WHEEL
statux-0.1.2.dist-info/top_level.txt
statux-0.1.2.dist-info/RECORD
