Metadata-Version: 1.1
Name: statux
Version: 0.1.2
Summary: Python module for hardware and system monitoring
Home-page: https://github.com/Arg0s1080/statux
Author: Ivan Rincon
Author-email: ivan.rincon76@gmail.com
License: GPLv3
Keywords: linux stats monitoring sensors proc sys battery cpu disk net ram hardware cpuinfo diskstats meminfo mounts partitions power_supply thermal temp
Platform: UNKNOWN
Classifier: Development Status :: 3 - Alpha
Classifier: License :: OSI Approved :: GNU General Public License v3 (GPLv3)
Classifier: Operating System :: POSIX :: Linux
Classifier: Programming Language :: Python :: 3
Classifier: Topic :: Software Development :: Libraries :: Python Modules
Classifier: Topic :: System :: Benchmark
Classifier: Topic :: System :: Hardware
Classifier: Topic :: System :: Networking :: Monitoring
Classifier: Topic :: System :: Operating System
Classifier: Topic :: Utilities
